sqls/__init__.py
sqls/sqls.py
sqlup-0.0.2.dist-info/METADATA
sqlup-0.0.2.dist-info/WHEEL
sqlup-0.0.2.dist-info/top_level.txt
sqlup-0.0.2.dist-info/RECORD
