Metadata-Version: 2.1
Name: sqlup
Version: 0.0.2
Summary: mysql_laod
Home-page: https://github.com/wisangyun/MyProject
Author: sang
Author-email: dnl6098@gamil.com
Classifier: Programming Language :: Python :: 3.6
Classifier: Programming Language :: Python :: 3.7
Classifier: Programming Language :: Python :: 3.8
Classifier: Programming Language :: Python :: 3.9
Requires-Python: >=3.6
Requires-Dist: pandas
Requires-Dist: sqlalchemy
Requires-Dist: mysql-connector-python
